estyp/__init__.py
estyp/cluster/__init__.py
estyp/linear_model/__init__.py
estyp/linear_model/stepwise/__init__.py
estyp/linear_model/stepwise/__base/__init__.py
estyp/testing/__init__.py
estyp/testing/__base/__init__.py
estyp-0.9.3.dist-info/METADATA
estyp-0.9.3.dist-info/WHEEL
estyp-0.9.3.dist-info/top_level.txt
estyp-0.9.3.dist-info/RECORD
