Metadata-Version: 2.1
Name: estyp
Version: 0.9.3
Summary: Extended Statistical Toolkit Yet Practical
Home-page: https://github.com/estebanrucan/estyp
Author: estebanrucan
Author-email: errucan@gmail.com
License: MIT
Project-URL: Bug Tracker, https://github.com/estebanrucan/estyp/issues
Project-URL: Homepage, https://github.com/estebanrucan/estyp
Classifier: Programming Language :: Python :: 3
Classifier: License :: OSI Approved :: MIT License
Classifier: Operating System :: OS Independent
Requires-Python: >=3.9.12
Requires-Dist: numpy >=1.22.3
Requires-Dist: scikit-learn >=1.3.0
Requires-Dist: matplotlib >=3.4.3
Requires-Dist: patsy >=0.5.3
Requires-Dist: statsmodels >=0.13.5
Requires-Dist: scipy >=1.10.1
Requires-Dist: kmodes >=0.12.2
Requires-Dist: tqdm >=4.65.0
Requires-Dist: joblib >=1.3.1
